conv_html_to_markdown-0.1.311.dist-info/METADATA
conv_html_to_markdown-0.1.311.dist-info/WHEEL
conv_html_to_markdown-0.1.311.dist-info/licenses/LICENSE
conv_html_to_markdown/__init__.py
conv_html_to_markdown/converter.py
conv_html_to_markdown/download_jina.py
conv_html_to_markdown/formatter.py
conv_html_to_markdown/main.py
conv_html_to_markdown/utils.py
conv_html_to_markdown-0.1.311.dist-info/RECORD
